ProTimer/__init__.py
ProTimer-0.1.0.dist-info/LICENCE.txt
ProTimer-0.1.0.dist-info/LICENSE
ProTimer-0.1.0.dist-info/METADATA
ProTimer-0.1.0.dist-info/WHEEL
ProTimer-0.1.0.dist-info/top_level.txt
ProTimer-0.1.0.dist-info/RECORD
