Metadata-Version: 2.1
Name: ProTimer
Version: 0.1.0
Summary: blocker to block programs until an event happens
Home-page: UNKNOWN
Author: Alawi Hussein Adnan Al Sayegh
Author-email: programming.laboratorys@gmail.com
License: MIT
Keywords: Timer,process,processers,Protime,"Process Time",blocker,blocking,blockit
Platform: UNKNOWN
Classifier: Development Status :: 5 - Production/Stable
Classifier: Intended Audience :: Developers
Classifier: License :: OSI Approved :: MIT License
Classifier: Programming Language :: Python :: 3
Requires-Dist: stopit
Requires-Dist: psutil
